odoo/addons/web_environment_ribbon/README.rst
odoo/addons/web_environment_ribbon/__init__.py
odoo/addons/web_environment_ribbon/__manifest__.py
odoo/addons/web_environment_ribbon/data/ribbon_data.xml
odoo/addons/web_environment_ribbon/i18n/ca.po
odoo/addons/web_environment_ribbon/i18n/de.po
odoo/addons/web_environment_ribbon/i18n/es.po
odoo/addons/web_environment_ribbon/i18n/fr.po
odoo/addons/web_environment_ribbon/i18n/hr.po
odoo/addons/web_environment_ribbon/i18n/it.po
odoo/addons/web_environment_ribbon/i18n/nl.po
odoo/addons/web_environment_ribbon/i18n/nl_NL.po
odoo/addons/web_environment_ribbon/i18n/pt.po
odoo/addons/web_environment_ribbon/i18n/pt_BR.po
odoo/addons/web_environment_ribbon/i18n/sl.po
odoo/addons/web_environment_ribbon/i18n/web_environment_ribbon.pot
odoo/addons/web_environment_ribbon/i18n/zh.po
odoo/addons/web_environment_ribbon/i18n/zh_CN.po
odoo/addons/web_environment_ribbon/models/__init__.py
odoo/addons/web_environment_ribbon/models/web_environment_ribbon_backend.py
odoo/addons/web_environment_ribbon/readme/CONFIGURE.md
odoo/addons/web_environment_ribbon/readme/CONTRIBUTORS.md
odoo/addons/web_environment_ribbon/readme/DESCRIPTION.md
odoo/addons/web_environment_ribbon/readme/USAGE.md
odoo/addons/web_environment_ribbon/static/description/configure_1.png
odoo/addons/web_environment_ribbon/static/description/icon.png
odoo/addons/web_environment_ribbon/static/description/index.html
odoo/addons/web_environment_ribbon/static/description/screenshot.png
odoo/addons/web_environment_ribbon/static/src/components/environment_ribbon/ribbon.css
odoo/addons/web_environment_ribbon/static/src/components/environment_ribbon/ribbon.esm.js
odoo/addons/web_environment_ribbon/tests/__init__.py
odoo/addons/web_environment_ribbon/tests/test_environment_ribbon_data.py
odoo_addon_web_environment_ribbon-19.0.1.0.0.2.dist-info/METADATA
odoo_addon_web_environment_ribbon-19.0.1.0.0.2.dist-info/WHEEL
odoo_addon_web_environment_ribbon-19.0.1.0.0.2.dist-info/top_level.txt
odoo_addon_web_environment_ribbon-19.0.1.0.0.2.dist-info/RECORD
